Assertions/4-Bit-Up-Counter/counter_4bit.sv
// Code your design here
module counter #(
    parameter WIDTH = 4
)(
    input  logic             clk,
    input  logic             rst_n,
    input  logic             en,
    output logic [WIDTH-1:0] count
);

    always_ff @(posedge clk) begin
        if (!rst_n)
            count <= 4'b0000;
        else if (en)
            count <= count + 1'b1;
    end

endmodule

Assertions/4-Bit-Up-Counter/counter_4bit_tb.sv
`timescale 1ns/1ps

module counter_tb;

    localparam WIDTH = 4;

    logic clk;
    logic rst_n;
    logic en;
    logic [WIDTH-1:0] count;

    
    counter #(.WIDTH(WIDTH)) dut (
        .clk   (clk),
        .rst_n (rst_n),
        .en    (en),
        .count (count)
    );

 
    initial begin 
      clk = 0;
    forever #5 clk = ~clk;
    end
  

    // ------------------------------------------------
    // Assertions
    // ------------------------------------------------

    // 1. Reset -> count must become 0
    assert_reset:
    assert property (@(posedge clk)
        !rst_n |=> count == '0
    );

    // 2. Enable low -> count must hold
    assert_hold:
    assert property (@(posedge clk)
        rst_n && !en |=> count == $past(count)
    );

    // 3. Enable high -> count must increment
    assert_increment:
    assert property (@(posedge clk)
        rst_n && en |=> count == ($past(count) + 1'b1)
    );

   
    initial begin
      
      $dumpfile("counter.vcd");
      $dumpvars(0, counter_tb);

        // Initial values
        rst_n = 0;
        en    = 0;

        // Apply reset
        repeat (2) @(negedge clk);

        // Release reset
        rst_n = 1;

        // --------------------------------------------
        // Test 1: Hold
        // --------------------------------------------
        en = 0;
        repeat (3) @(negedge clk);

        // --------------------------------------------
        // Test 2: Count
        // --------------------------------------------
        en = 1;
        repeat (5) @(negedge clk);

        // --------------------------------------------
        // Test 3: Hold again
        // --------------------------------------------
        en = 0;
        repeat (3) @(negedge clk);

        // --------------------------------------------
        // Test 4: Rollover
        // --------------------------------------------
        en = 1;
        repeat (20) @(negedge clk);

        // --------------------------------------------
        // Test 5: Reset has priority over enable
        // --------------------------------------------
        rst_n = 0;
        en    = 1;
        repeat (2) @(negedge clk);

        // Finish
        $finish;
    end

endmodule

Assertions/4-Bit-Up-Counter/counter_4bit.vcd
$date
    Aug 17, 2026  12:00:48
$end
$version
    TOOL:	xmsim(64)	23.09-s007
$end
$timescale
    1 ps
$end

$scope module counter_tb $end
$var parameter 32 !    WIDTH $end
$var reg       1 "    clk $end
$var reg       1 #    rst_n $end
$var reg       1 $    en $end
$var reg       4 %    count [3:0] $end

$scope module dut $end
$var parameter 32 &    WIDTH $end
$var wire      1 '    clk  $end
$var wire      1 (    rst_n  $end
$var wire      1 )    en  $end
$var reg       4 *    count [3:0] $end
$upscope $end

$upscope $end

$enddefinitions $end
$dumpvars
b100 &
b100 !
0"
0#
0$
bx %
0'
0(
0)
bx *
$end
#5000
1"
1'
b0 *
b0 %
#10000
0"
0'
#15000
1"
1'
#20000
0"
1#
1(
0'
#25000
1"
1'
#30000
0"
0'
#35000
1"
1'
#40000
0"
0'
#45000
1"
1'
#50000
0"
1$
1)
0'
#55000
1"
1'
b1 *
b1 %
#60000
0"
0'
#65000
1"
1'
b10 *
b10 %
#70000
0"
0'
#75000
1"
1'
b11 *
b11 %
#80000
0"
0'
#85000
1"
1'
b100 *
b100 %
#90000
0"
0'
#95000
1"
1'
b101 *
b101 %
#100000
0"
0$
0)
0'
#105000
1"
1'
#110000
0"
0'
#115000
1"
1'
#120000
0"
0'
#125000
1"
1'
#130000
0"
1$
1)
0'
#135000
1"
1'
b110 *
b110 %
#140000
0"
0'
#145000
1"
1'
b111 *
b111 %
#150000
0"
0'
#155000
1"
1'
b1000 *
b1000 %
#160000
0"
0'
#165000
1"
1'
b1001 *
b1001 %
#170000
0"
0'
#175000
1"
1'
b1010 *
b1010 %
#180000
0"
0'
#185000
1"
1'
b1011 *
b1011 %
#190000
0"
0'
#195000
1"
1'
b1100 *
b1100 %
#200000
0"
0'
#205000
1"
1'
b1101 *
b1101 %
#210000
0"
0'
#215000
1"
1'
b1110 *
b1110 %
#220000
0"
0'
#225000
1"
1'
b1111 *
b1111 %
#230000
0"
0'
#235000
1"
1'
b0 *
b0 %
#240000
0"
0'
#245000
1"
1'
b1 *
b1 %
#250000
0"
0'
#255000
1"
1'
b10 *
b10 %
#260000
0"
0'
#265000
1"
1'
b11 *
b11 %
#270000
0"
0'
#275000
1"
1'
b100 *
b100 %
#280000
0"
0'
#285000
1"
1'
b101 *
b101 %
#290000
0"
0'
#295000
1"
1'
b110 *
b110 %
#300000
0"
0'
#305000
1"
1'
b111 *
b111 %
#310000
0"
0'
#315000
1"
1'
b1000 *
b1000 %
#320000
0"
0'
#325000
1"
1'
b1001 *
b1001 %
#330000
0"
0#
0(
0'
#335000
1"
1'
b0 *
b0 %
